[{"ayah_number":1,"text_arabic":"أَلَمْ نَشْرَحْ لَكَ صَدْرَكَ","surah_id":94},{"ayah_number":2,"text_arabic":"وَوَضَعْنَا عَنْكَ وِزْرَكَ  الَّذِي أَنْقَضَ ظَهْرَكَ","surah_id":94,"covers_ayahs":"2-3"},{"ayah_number":4,"text_arabic":"وَرَفَعْنَا لَكَ ذِكْرَكَ","surah_id":94},{"ayah_number":5,"text_arabic":"فَإِنَّ مَعَ الْعُسْرِ يُسْرًا  إِنَّ مَعَ الْعُسْرِ يُسْرًا","surah_id":94,"covers_ayahs":"5-6"},{"ayah_number":7,"text_arabic":"فَإِذَا فَرَغْتَ فَانْصَبْ","surah_id":94},{"ayah_number":8,"text_arabic":"وَإِلَى رَبِّكَ فَارْغَبْ","surah_id":94}]